sztaki/__init__.py
sztaki/models.py
sztaki/translator.py
sztaki-0.1.4.dist-info/LICENSE
sztaki-0.1.4.dist-info/METADATA
sztaki-0.1.4.dist-info/WHEEL
sztaki-0.1.4.dist-info/top_level.txt
sztaki-0.1.4.dist-info/RECORD
