Metadata-Version: 2.1
Name: sztaki
Version: 0.1.4
Summary: Hungarian to English words tranlator
Home-page: https://github.com/adyachok/sztaki
Author: Andras Gyacsok
Author-email: atti.dyachok@gmail.com
License: MIT
Platform: UNKNOWN
License-File: LICENSE
Requires-Dist: beautifulsoup4
Requires-Dist: dataclasses-json
Requires-Dist: googletrans (==4.0.0rc1)
